assets/cat-weather-bot.gif
assets/messages.json
assets/img/chilly/5476f3647058e196f659c80e5d2c924f.jpg
assets/img/chilly/6a2ca38cad64864d9ff97d694a84fb62.jpg
assets/img/chilly/accd19f6055aba394b69a1ebe93f0489.jpg
assets/img/cold/33d09363d41c65be6f4dfde3ac496bd3.jpg
assets/img/cold/82de5a11540dd6858608adbf7bb7c9ca.jpg
assets/img/cold/dcb2d94f4e6eb38af7b3bef5d5475f26.jpg
assets/img/hot/2129fc8105820874182f695137774fcb.jpg
assets/img/hot/2df15a214ccd2adab0f96127a8271db9.jpeg
assets/img/hot/a9062eb901554c9eae7353c3b4948e48.jpg
assets/img/mild/2df15a214ccd2adab0f96127a8271db9.jpg
assets/img/mild/aef9ed10bbb9dc84c1f5c872197e6cb9.jpg
assets/img/very_cold/33d09363d41c65be6f4dfde3ac496bd2.jpg
assets/img/very_cold/33d09363d41c65be6f4dfde3ac496bd77.jpg
assets/img/very_cold/90ae886e7c0bc36550423e9129998633.jpg
assets/img/very_cold/90ae886e7c0bc36550423e91299986df.jpg
assets/img/very_hot/0cbf94eaf35247980a0e524716b40d9f.jpg
assets/img/very_hot/590328b1121b3fe3139bdeb464f269df.jpg
assets/img/very_hot/6e03ea0642c078cca9e078e1aa2993ba.jpg
assets/img/very_hot/80eb6d43fbea65cbe96f37be86e89dd1.jpg
assets/logo/cat-weather-bot.png
cat_weather_bot/__init__.py
cat_weather_bot/__main__.py
cat_weather_bot/config.py
cat_weather_bot/models.py
cat_weather_bot/thermal_sensation.py
cat_weather_bot/weather_api.py
cat_weather_bot/weather_bot.py
cat_weather_bot-0.2.1.dist-info/LICENSE.md
cat_weather_bot-0.2.1.dist-info/METADATA
cat_weather_bot-0.2.1.dist-info/WHEEL
cat_weather_bot-0.2.1.dist-info/entry_points.txt
cat_weather_bot-0.2.1.dist-info/top_level.txt
cat_weather_bot-0.2.1.dist-info/RECORD
