Metadata-Version: 2.1
Name: cat-weather-bot
Version: 0.2.1
Summary: Cat Weather Bot is a Telegram bot that receives a location sented by the user and returns the temperature and apparent temperature that location.
Author-email: Icaro Henrique <icaro.henrique001@gmail.com>
License: MIT License
Project-URL: Homepage, https://github.com/icaroHenrique/cat-weather-bot
Keywords: weather,bot,weather bot
Classifier: Programming Language :: Python :: 3
Classifier: License :: OSI Approved :: MIT License
Classifier: Operating System :: OS Independent
Requires-Python: >=3.12
License-File: LICENSE.md
Requires-Dist: requests ==2.28.2
Requires-Dist: python-telegram-bot ==20.7
Requires-Dist: dynaconf ==3.2.4
Requires-Dist: python-dotenv ==1.0.0
Requires-Dist: filetype
Provides-Extra: dev
Requires-Dist: pytest ; extra == 'dev'
Requires-Dist: pytest-watch ; extra == 'dev'
Requires-Dist: pytest-forked ; extra == 'dev'
Requires-Dist: flake8 ; extra == 'dev'
Requires-Dist: pyproject-flake8 ; extra == 'dev'
Requires-Dist: black ; extra == 'dev'
Requires-Dist: isort ; extra == 'dev'
Requires-Dist: ipython <=8.0.0,>=7.0.0 ; extra == 'dev'
Requires-Dist: ipdb ; extra == 'dev'
Requires-Dist: pudb ; extra == 'dev'
Requires-Dist: requests ==2.28.2 ; extra == 'dev'
Requires-Dist: python-telegram-bot ==20.7 ; extra == 'dev'
Requires-Dist: dynaconf ==3.2.4 ; extra == 'dev'
Requires-Dist: python-dotenv ==1.0.0 ; extra == 'dev'
Requires-Dist: filetype ; extra == 'dev'
Provides-Extra: test
Requires-Dist: pytest ; extra == 'test'
Requires-Dist: pytest-watch ; extra == 'test'
Requires-Dist: pytest-forked ; extra == 'test'
Requires-Dist: flake8 ; extra == 'test'
Requires-Dist: pyproject-flake8 ; extra == 'test'
Requires-Dist: black ; extra == 'test'
Requires-Dist: isort ; extra == 'test'
